nonebot_plugin_cd_manager-0.1.2.dist-info/METADATA
nonebot_plugin_cd_manager-0.1.2.dist-info/WHEEL
nonebot_plugin_cd_manager-0.1.2.dist-info/entry_points.txt
nonebot_plugin_cd_manager-0.1.2.dist-info/licenses/LICENSE
nonebot_plugin_cd_manager/__init__.py
nonebot_plugin_cd_manager/cd_manager.py
nonebot_plugin_cd_manager/config.py
nonebot_plugin_cd_manager/data_manager.py
nonebot_plugin_cd_manager/matcher.py
nonebot_plugin_cd_manager/matcher_utils.py
nonebot_plugin_cd_manager-0.1.2.dist-info/RECORD
